mcda/__init__.py
mcda/categories.py
mcda/functions.py
mcda/matrices.py
mcda/plot.py
mcda/py.typed
mcda/relations.py
mcda/scales.py
mcda/set_functions.py
mcda/transformers.py
mcda/types.py
mcda/values.py
mcda/internal/__init__.py
mcda/internal/core/__init__.py
mcda/internal/core/aggregators.py
mcda/internal/core/aliases.py
mcda/internal/core/categories.py
mcda/internal/core/compatibility.py
mcda/internal/core/criteria_functions.py
mcda/internal/core/functions.py
mcda/internal/core/interfaces.py
mcda/internal/core/matrices.py
mcda/internal/core/relations.py
mcda/internal/core/scales.py
mcda/internal/core/set_functions.py
mcda/internal/core/transformers.py
mcda/internal/core/utils.py
mcda/internal/core/values.py
mcda/internal/dea/__init__.py
mcda/internal/mavt/__init__.py
mcda/internal/mavt/uta.py
mcda/internal/outranking/__init__.py
mcda/internal/outranking/electre.py
mcda/internal/outranking/mrsort.py
mcda/internal/outranking/promethee.py
mcda/internal/outranking/srmp.py
mcda/internal/plot/__init__.py
mcda/internal/plot/plot.py
mcda/mavt/__init__.py
mcda/mavt/aggregators.py
mcda/mavt/uta.py
mcda/outranking/__init__.py
mcda/outranking/electre.py
mcda/outranking/mrsort.py
mcda/outranking/promethee.py
mcda/outranking/srmp.py
mcda-1.1.0.dist-info/licenses/LICENSE
mcda-1.1.0.dist-info/METADATA
mcda-1.1.0.dist-info/WHEEL
mcda-1.1.0.dist-info/top_level.txt
mcda-1.1.0.dist-info/RECORD
