Metadata-Version: 2.4
Name: mcda
Version: 1.1.0
Summary: Package for Multi Criteria Decision Analysis
Author-email: Nicolas Duminy <nicolas.duminy@imt-atlantique.fr>, Patrick Meyer <patrick.meyer@imt-atlantique.fr>
License: Copyright IMT Atlantique, 2021
Project-URL: Homepage, https://py-mcda.readthedocs.io
Project-URL: Source, https://gitlab.com/decide.imt-atlantique/pymcda
Project-URL: Issues, https://gitlab.com/decide.imt-atlantique/pymcda/issues
Classifier: Development Status :: 5 - Production/Stable
Classifier: Intended Audience :: Developers
Classifier: Intended Audience :: Science/Research
Classifier: License :: OSI Approved :: European Union Public Licence 1.2 (EUPL 1.2)
Classifier: Operating System :: OS Independent
Classifier: Programming Language :: Python :: 3
Classifier: Programming Language :: Python :: 3 :: Only
Classifier: Topic :: Scientific/Engineering :: Mathematics
Requires-Python: >=3.9
License-File: LICENSE
Requires-Dist: numpy
Requires-Dist: pulp
Requires-Dist: scikit-learn
Requires-Dist: pandas
Requires-Dist: Deprecated
Requires-Dist: typing_extensions; python_version < "3.11"
Provides-Extra: plot
Requires-Dist: graphviz; extra == "plot"
Requires-Dist: matplotlib; extra == "plot"
Provides-Extra: all
Requires-Dist: mcda[plot]; extra == "all"
Dynamic: license-file
